torchyield/__init__.py
torchyield/factory.py
torchyield/layers.py
torchyield/utils.py
torchyield/verbose.py
torchyield-0.4.0.dist-info/WHEEL
torchyield-0.4.0.dist-info/METADATA
torchyield-0.4.0.dist-info/RECORD
