Metadata-Version: 2.3
Name: torchyield
Version: 0.4.0
Summary: Make PyTorch models using generator functions.
Author-email: Kale Kundert <kale@thekunderts.net>
Requires-Python: ~=3.10
Classifier: Programming Language :: Python :: 3.10
Requires-Dist: more_itertools
Requires-Dist: torch
Requires-Dist: sphinx ; extra == "doc"
Requires-Dist: sphinx_rtd_theme ; extra == "doc"
Requires-Dist: pytest ; extra == "test"
Project-URL: Bug Tracker, https://github.com/kalekundert/torchyield/issues
Project-URL: Continuous Integration, https://github.com/kalekundert/torchyield/actions
Project-URL: Documentation, https://torch-fuel.readthedocs.io/en/latest/
Project-URL: Test Coverage, https://app.codecov.io/github/kalekundert/torchyield
Project-URL: Version Control, https://github.com/kalekundert/torchyield
Provides-Extra: doc
Provides-Extra: test
